[{"tahun": 2020, "provinsi": "GORONTALO", "suhu_rata_c": 26.865486122157407, "curah_hujan_mm": 2478.583346588886, "kelembaban_persen": 80.16371530539351, "hari_hujan": 150}, {"tahun": 2021, "provinsi": "GORONTALO", "suhu_rata_c": 26.765648422225084, "curah_hujan_mm": 2358.778106670099, "kelembaban_persen": 79.9141210555627, "hari_hujan": 149}, {"tahun": 2022, "provinsi": "GORONTALO", "suhu_rata_c": 27.463741391909284, "curah_hujan_mm": 3196.4896702911415, "kelembaban_persen": 81.65935347977322, "hari_hujan": 159}, {"tahun": 2023, "provinsi": "GORONTALO", "suhu_rata_c": 26.66835197489368, "curah_hujan_mm": 2242.0223698724158, "kelembaban_persen": 79.6708799372342, "hari_hujan": 148}, {"tahun": 2024, "provinsi": "GORONTALO", "suhu_rata_c": 26.654614739749977, "curah_hujan_mm": 2225.53768769997, "kelembaban_persen": 79.63653684937493, "hari_hujan": 147}]